<?xml version="1.0" encoding="UTF-8" ?>
<!DOCTYPE mapper PUBLIC "-//mybatis.org//DTD Mapper 3.0//EN" "http://mybatis.org/dtd/mybatis-3-mapper.dtd" >
<mapper namespace="com.ttl.myspringboot.dao.gzb01_t_sum_roleMapper" >
  <resultMap id="BaseResultMap" type="com.ttl.myspringboot.po.gzb01_t_sum_role" >
    <!--
      WARNING - @mbggenerated
      This element is automatically generated by MyBatis Generator, do not modify.
    -->
    <result column="sum_role_id" property="sumRoleId" jdbcType="INTEGER" />
    <result column="sum_role_name" property="sumRoleName" jdbcType="VARCHAR" />
    <result column="sum_role_desc" property="sumRoleDesc" jdbcType="VARCHAR" />
    <result column="sum_role_type" property="sumRoleType" jdbcType="INTEGER" />
    <result column="sum_role_app" property="sumRoleApp" jdbcType="INTEGER" />
    <result column="sum_role_status" property="sumRoleStatus" jdbcType="TINYINT" />
  </resultMap>
  <sql id="Example_Where_Clause" >
    <!--
      WARNING - @mbggenerated
      This element is automatically generated by MyBatis Generator, do not modify.
    -->
    <where >
      <foreach collection="oredCriteria" item="criteria" separator="or" >
        <if test="criteria.valid" >
          <trim prefix="(" suffix=")" prefixOverrides="and" >
            <foreach collection="criteria.criteria" item="criterion" >
              <choose >
                <when test="criterion.noValue" >
                  and ${criterion.condition}
                </when>
                <when test="criterion.singleValue" >
                  and ${criterion.condition} #{criterion.value}
                </when>
                <when test="criterion.betweenValue" >
                  and ${criterion.condition} #{criterion.value} and #{criterion.secondValue}
                </when>
                <when test="criterion.listValue" >
                  and ${criterion.condition}
                  <foreach collection="criterion.value" item="listItem" open="(" close=")" separator="," >
                    #{listItem}
                  </foreach>
                </when>
              </choose>
            </foreach>
          </trim>
        </if>
      </foreach>
    </where>
  </sql>
  <sql id="Update_By_Example_Where_Clause" >
    <!--
      WARNING - @mbggenerated
      This element is automatically generated by MyBatis Generator, do not modify.
    -->
    <where >
      <foreach collection="example.oredCriteria" item="criteria" separator="or" >
        <if test="criteria.valid" >
          <trim prefix="(" suffix=")" prefixOverrides="and" >
            <foreach collection="criteria.criteria" item="criterion" >
              <choose >
                <when test="criterion.noValue" >
                  and ${criterion.condition}
                </when>
                <when test="criterion.singleValue" >
                  and ${criterion.condition} #{criterion.value}
                </when>
                <when test="criterion.betweenValue" >
                  and ${criterion.condition} #{criterion.value} and #{criterion.secondValue}
                </when>
                <when test="criterion.listValue" >
                  and ${criterion.condition}
                  <foreach collection="criterion.value" item="listItem" open="(" close=")" separator="," >
                    #{listItem}
                  </foreach>
                </when>
              </choose>
            </foreach>
          </trim>
        </if>
      </foreach>
    </where>
  </sql>
  <sql id="Base_Column_List" >
    <!--
      WARNING - @mbggenerated
      This element is automatically generated by MyBatis Generator, do not modify.
    -->
    sum_role_id, sum_role_name, sum_role_desc, sum_role_type, sum_role_app, sum_role_status
  </sql>
  <select id="selectByExample" resultMap="BaseResultMap" parameterType="com.ttl.myspringboot.po.gzb01_t_sum_roleExample" >
    <!--
      WARNING - @mbggenerated
      This element is automatically generated by MyBatis Generator, do not modify.
    -->
    select
    <if test="distinct" >
      distinct
    </if>
    'true' as QUERYID,
    <include refid="Base_Column_List" />
    from gzb01_t_sum_role
    <if test="_parameter != null" >
      <include refid="Example_Where_Clause" />
    </if>
    <if test="orderByClause != null" >
      order by ${orderByClause}
    </if>
  </select>
  <delete id="deleteByExample" parameterType="com.ttl.myspringboot.po.gzb01_t_sum_roleExample" >
    <!--
      WARNING - @mbggenerated
      This element is automatically generated by MyBatis Generator, do not modify.
    -->
    delete from gzb01_t_sum_role
    <if test="_parameter != null" >
      <include refid="Example_Where_Clause" />
    </if>
  </delete>
  <insert id="insert" parameterType="com.ttl.myspringboot.po.gzb01_t_sum_role" >
    <!--
      WARNING - @mbggenerated
      This element is automatically generated by MyBatis Generator, do not modify.
    -->
    insert into gzb01_t_sum_role (sum_role_id, sum_role_name, sum_role_desc, 
      sum_role_type, sum_role_app, sum_role_status
      )
    values (#{sumRoleId,jdbcType=INTEGER}, #{sumRoleName,jdbcType=VARCHAR}, #{sumRoleDesc,jdbcType=VARCHAR}, 
      #{sumRoleType,jdbcType=INTEGER}, #{sumRoleApp,jdbcType=INTEGER}, #{sumRoleStatus,jdbcType=TINYINT}
      )
  </insert>
  <insert id="insertSelective" parameterType="com.ttl.myspringboot.po.gzb01_t_sum_role" >
    <!--
      WARNING - @mbggenerated
      This element is automatically generated by MyBatis Generator, do not modify.
    -->
    insert into gzb01_t_sum_role
    <trim prefix="(" suffix=")" suffixOverrides="," >
      <if test="sumRoleId != null" >
        sum_role_id,
      </if>
      <if test="sumRoleName != null" >
        sum_role_name,
      </if>
      <if test="sumRoleDesc != null" >
        sum_role_desc,
      </if>
      <if test="sumRoleType != null" >
        sum_role_type,
      </if>
      <if test="sumRoleApp != null" >
        sum_role_app,
      </if>
      <if test="sumRoleStatus != null" >
        sum_role_status,
      </if>
    </trim>
    <trim prefix="values (" suffix=")" suffixOverrides="," >
      <if test="sumRoleId != null" >
        #{sumRoleId,jdbcType=INTEGER},
      </if>
      <if test="sumRoleName != null" >
        #{sumRoleName,jdbcType=VARCHAR},
      </if>
      <if test="sumRoleDesc != null" >
        #{sumRoleDesc,jdbcType=VARCHAR},
      </if>
      <if test="sumRoleType != null" >
        #{sumRoleType,jdbcType=INTEGER},
      </if>
      <if test="sumRoleApp != null" >
        #{sumRoleApp,jdbcType=INTEGER},
      </if>
      <if test="sumRoleStatus != null" >
        #{sumRoleStatus,jdbcType=TINYINT},
      </if>
    </trim>
  </insert>
  <select id="countByExample" parameterType="com.ttl.myspringboot.po.gzb01_t_sum_roleExample" resultType="java.lang.Integer" >
    <!--
      WARNING - @mbggenerated
      This element is automatically generated by MyBatis Generator, do not modify.
    -->
    select count(*) from gzb01_t_sum_role
    <if test="_parameter != null" >
      <include refid="Example_Where_Clause" />
    </if>
  </select>
  <update id="updateByExampleSelective" parameterType="map" >
    <!--
      WARNING - @mbggenerated
      This element is automatically generated by MyBatis Generator, do not modify.
    -->
    update gzb01_t_sum_role
    <set >
      <if test="record.sumRoleId != null" >
        sum_role_id = #{record.sumRoleId,jdbcType=INTEGER},
      </if>
      <if test="record.sumRoleName != null" >
        sum_role_name = #{record.sumRoleName,jdbcType=VARCHAR},
      </if>
      <if test="record.sumRoleDesc != null" >
        sum_role_desc = #{record.sumRoleDesc,jdbcType=VARCHAR},
      </if>
      <if test="record.sumRoleType != null" >
        sum_role_type = #{record.sumRoleType,jdbcType=INTEGER},
      </if>
      <if test="record.sumRoleApp != null" >
        sum_role_app = #{record.sumRoleApp,jdbcType=INTEGER},
      </if>
      <if test="record.sumRoleStatus != null" >
        sum_role_status = #{record.sumRoleStatus,jdbcType=TINYINT},
      </if>
    </set>
    <if test="_parameter != null" >
      <include refid="Update_By_Example_Where_Clause" />
    </if>
  </update>
  <update id="updateByExample" parameterType="map" >
    <!--
      WARNING - @mbggenerated
      This element is automatically generated by MyBatis Generator, do not modify.
    -->
    update gzb01_t_sum_role
    set sum_role_id = #{record.sumRoleId,jdbcType=INTEGER},
      sum_role_name = #{record.sumRoleName,jdbcType=VARCHAR},
      sum_role_desc = #{record.sumRoleDesc,jdbcType=VARCHAR},
      sum_role_type = #{record.sumRoleType,jdbcType=INTEGER},
      sum_role_app = #{record.sumRoleApp,jdbcType=INTEGER},
      sum_role_status = #{record.sumRoleStatus,jdbcType=TINYINT}
    <if test="_parameter != null" >
      <include refid="Update_By_Example_Where_Clause" />
    </if>
  </update>
</mapper>